{
  "id": "95143532-128d-400b-ba42-0bc70501ebd0",
  "prevId": "f900cb7f-730a-4df1-a5be-4f3c438629c0",
  "version": "7",
  "dialect": "postgresql",
  "tables": {
    "public.exercises": {
      "name": "exercises",
      "schema": "",
      "columns": {
        "id": {
          "name": "id",
          "type": "serial",
          "primaryKey": true,
          "notNull": true
        },
        "name": {
          "name": "name",
          "type": "varchar(300)",
          "primaryKey": false,
          "notNull": false
        },
        "info": {
          "name": "info",
          "type": "text",
          "primaryKey": false,
          "notNull": false
        },
        "createdBy": {
          "name": "createdBy",
          "type": "integer",
          "primaryKey": false,
          "notNull": false
        }
      },
      "indexes": {},
      "foreignKeys": {
        "exercises_createdBy_users_id_fk": {
          "name": "exercises_createdBy_users_id_fk",
          "tableFrom": "exercises",
          "tableTo": "users",
          "columnsFrom": [
            "createdBy"
          ],
          "columnsTo": [
            "id"
          ],
          "onDelete": "no action",
          "onUpdate": "no action"
        }
      },
      "compositePrimaryKeys": {},
      "uniqueConstraints": {}
    },
    "public.users": {
      "name": "users",
      "schema": "",
      "columns": {
        "id": {
          "name": "id",
          "type": "serial",
          "primaryKey": true,
          "notNull": true
        },
        "email": {
          "name": "email",
          "type": "varchar(400)",
          "primaryKey": false,
          "notNull": true
        },
        "googleId": {
          "name": "googleId",
          "type": "varchar(500)",
          "primaryKey": false,
          "notNull": false
        }
      },
      "indexes": {},
      "foreignKeys": {},
      "compositePrimaryKeys": {},
      "uniqueConstraints": {
        "users_email_unique": {
          "name": "users_email_unique",
          "nullsNotDistinct": false,
          "columns": [
            "email"
          ]
        }
      }
    }
  },
  "enums": {},
  "schemas": {},
  "_meta": {
    "columns": {},
    "schemas": {},
    "tables": {}
  }
}